2.4/counter_nbit.v
module counter_nbit #(parameter WIDTH = 4)(
    input clk,
    input reset,
    input enable,
    input [WIDTH-1:0] data,
    input load,
    input up_down,
    output reg [WIDTH-1:0] count
);

always @(posedge clk or posedge reset) begin
    if (reset)
        count <= 0;
    else if (load)
        count <= data;
    else if (enable)
        count <= up_down ? (count + 1'b1) : (count - 1'b1);
end

endmodule

2.4/timer_60.v
module timer_60(
    input clk,
    input reset,
    input enable,      // This enable should already be divided clock (e.g., every 5 cycles)
    output reg [3:0] low_digit,
    output reg [2:0] high_digit
);

    reg low_load;
    reg high_load;
    reg high_enable;

    wire [3:0] low_count;
    wire [2:0] high_count;

    // Internal counters for low and high digits
    counter_nbit #(.WIDTH(4)) LD (
        .clk(clk),
        .reset(reset),
        .enable(enable),
        .data(4'b0000),
        .load(low_load),
        .up_down(1'b1),
        .count(low_count)
    );

    counter_nbit #(.WIDTH(3)) HD (
        .clk(clk),
        .reset(reset),
        .enable(high_enable),
        .data(3'b000),
        .load(high_load),
        .up_down(1'b1),
        .count(high_count)
    );

    // Combinational logic to control loading and enabling counters
    always @(*) begin
        low_load = 0;
        high_load = 0;
        high_enable = 0;

        if (enable) begin
            if (low_count == 9 && high_count == 5) begin
                // At 59 → reset both counters
                low_load = 1;
                high_load = 1;
            end else if (low_count == 9) begin
                // At 9 → reset low digit and enable high digit to increment
                low_load = 1;
                high_enable = 1;
            end
        end
    end

    // Update outputs synchronously
    always @(posedge clk or posedge reset) begin
        if (reset) begin
            low_digit <= 0;
            high_digit <= 0;
        end else begin
            low_digit <= low_count;
            high_digit <= high_count;
        end
    end

endmodule

2.4/timer_60_tb.v
`timescale 1ns/1ns

module timer_60_tb;

    reg clk;
    reg reset;
    reg enable;
    wire [3:0] low_digit;
    wire [2:0] high_digit;

    // Instantiate the DUT
    timer_60 uut (
        .clk(clk),
        .reset(reset),
        .enable(enable),
        .low_digit(low_digit),
        .high_digit(high_digit)
    );

    // Generate a clock: fast so we can see changes
    initial begin
        clk = 0;
        forever #5 clk = ~clk;  // 10ns clock period
    end

    initial begin
        // Waveform dump
        $dumpfile("timer_60_tb.vcd");
        $dumpvars(0, timer_60_tb);

        // Initial conditions
        reset = 1;
        enable = 0;

        #10 reset = 0;
        #10 enable = 1;
    end

endmodule

2.4/timer_60_tb.vcd
$date
	Sat Aug 02 23:43:03 2025
$end
$version
	ModelSim Version 2020.1
$end
$timescale
	1ns
$end

$scope module timer_60_tb $end
$var reg 1 ! clk $end
$var reg 1 " reset $end
$var reg 1 # enable $end
$var wire 1 $ low_digit [3] $end
$var wire 1 % low_digit [2] $end
$var wire 1 & low_digit [1] $end
$var wire 1 ' low_digit [0] $end
$var wire 1 ( high_digit [2] $end
$var wire 1 ) high_digit [1] $end
$var wire 1 * high_digit [0] $end

$scope module uut $end
$var wire 1 + clk $end
$var wire 1 , reset $end
$var wire 1 - enable $end
$var reg 4 . low_digit [3:0] $end
$var reg 3 / high_digit [2:0] $end
$var reg 1 0 low_load $end
$var reg 1 1 high_load $end
$var reg 1 2 high_enable $end
$var wire 1 3 low_count [3] $end
$var wire 1 4 low_count [2] $end
$var wire 1 5 low_count [1] $end
$var wire 1 6 low_count [0] $end
$var wire 1 7 high_count [2] $end
$var wire 1 8 high_count [1] $end
$var wire 1 9 high_count [0] $end

$scope module LD $end
$var parameter 32 : WIDTH $end
$var wire 1 + clk $end
$var wire 1 , reset $end
$var wire 1 - enable $end
$var wire 1 ; data [3] $end
$var wire 1 < data [2] $end
$var wire 1 = data [1] $end
$var wire 1 > data [0] $end
$var wire 1 ? load $end
$var wire 1 @ up_down $end
$var reg 4 A count [3:0] $end
$upscope $end

$scope module HD $end
$var parameter 32 B WIDTH $end
$var wire 1 + clk $end
$var wire 1 , reset $end
$var wire 1 C enable $end
$var wire 1 D data [2] $end
$var wire 1 E data [1] $end
$var wire 1 F data [0] $end
$var wire 1 G load $end
$var wire 1 H up_down $end
$var reg 3 I count [2:0] $end
$upscope $end
$upscope $end
$upscope $end
$enddefinitions $end
#0
$dumpvars
0!
1"
0#
b0 .
b0 /
00
01
02
b0 A
b0 I
b100 :
b11 B
0'
0&
0%
0$
0*
0)
0(
06
05
04
03
09
08
07
0-
1,
0+
1H
0G
0F
0E
0D
0C
1@
0?
0>
0=
0<
0;
$end
#5
1!
1+
#10
0"
0!
0,
0+
#15
1!
1+
#20
1#
0!
1-
0+
#25
1!
1+
b1 A
16
#30
0!
0+
#35
1!
1+
b1 .
1'
b10 A
06
15
#40
0!
0+
#45
1!
1+
b10 .
0'
1&
b11 A
16
#50
0!
0+
#55
1!
1+
b11 .
1'
b100 A
06
05
14
#60
0!
0+
#65
1!
1+
b100 .
0'
0&
1%
b101 A
16
#70
0!
0+
#75
1!
1+
b101 .
1'
b110 A
06
15
#80
0!
0+
#85
1!
1+
b110 .
0'
1&
b111 A
16
#90
0!
0+
#95
1!
1+
b111 .
1'
b1000 A
06
05
04
13
#100
0!
0+
#105
1!
1+
b1000 .
0'
0&
0%
1$
b1001 A
16
#110
0!
0+
#115
1!
1+
b1001 .
10
12
1'
1?
1C
b1010 A
06
15
#120
0!
0+
#125
1!
1+
b1010 .
00
02
0'
1&
0?
0C
b0 A
b1 I
19
05
03
#130
0!
0+
#135
1!
1+
b0 .
b1 /
1*
0&
0$
b1 A
16
#140
0!
0+
#145
1!
1+
b1 .
1'
b10 A
06
15
#150
0!
0+
#155
1!
1+
b10 .
0'
1&
b11 A
16
#160
0!
0+
#165
1!
1+
b11 .
1'
b100 A
06
05
14
#170
0!
0+
#175
1!
1+
b100 .
0'
0&
1%
b101 A
16
#180
0!
0+
#185
1!
1+
b101 .
1'
b110 A
06
15
#190
0!
0+
#195
1!
1+
b110 .
0'
1&
b111 A
16
#200
0!
0+
#205
1!
1+
b111 .
1'
b1000 A
06
05
04
13
#210
0!
0+
#215
1!
1+
b1000 .
0'
0&
0%
1$
b1001 A
16
#220
0!
0+
#225
1!
1+
b1001 .
10
12
1'
1?
1C
b1010 A
06
15
#230
0!
0+
#235
1!
1+
b1010 .
00
02
0'
1&
0?
0C
b0 A
b10 I
09
18
05
03
#240
0!
0+
#245
1!
1+
b0 .
b10 /
0*
1)
0&
0$
b1 A
16
#250
0!
0+
#255
1!
1+
b1 .
1'
b10 A
06
15
#260
0!
0+
#265
1!
1+
b10 .
0'
1&
b11 A
16
#270
0!
0+
#275
1!
1+
b11 .
1'
b100 A
06
05
14
#280
0!
0+
#285
1!
1+
b100 .
0'
0&
1%
b101 A
16
#290
0!
0+
#295
1!
1+
b101 .
1'
b110 A
06
15
#300
0!
0+
#305
1!
1+
b110 .
0'
1&
b111 A
16
#310
0!
0+
#315
1!
1+
b111 .
1'
b1000 A
06
05
04
13
#320
0!
0+
#325
1!
1+
b1000 .
0'
0&
0%
1$
b1001 A
16
#330
0!
0+
#335
1!
1+
b1001 .
10
12
1'
1?
1C
b1010 A
06
15
#340
0!
0+
#345
1!
1+
b1010 .
00
02
0'
1&
0?
0C
b0 A
b11 I
19
05
03
#350
0!
0+
#355
1!
1+
b0 .
b11 /
1*
0&
0$
b1 A
16
#360
0!
0+
#365
1!
1+
b1 .
1'
b10 A
06
15
#370
0!
0+
#375
1!
1+
b10 .
0'
1&
b11 A
16
#380
0!
0+
#385
1!
1+
b11 .
1'
b100 A
06
05
14
#390
0!
0+
#395
1!
1+
b100 .
0'
0&
1%
b101 A
16
#400
0!
0+
#405
1!
1+
b101 .
1'
b110 A
06
15
#410
0!
0+
#415
1!
1+
b110 .
0'
1&
b111 A
16
#420
0!
0+
#425
1!
1+
b111 .
1'
b1000 A
06
05
04
13
#430
0!
0+
#435
1!
1+
b1000 .
0'
0&
0%
1$
b1001 A
16
#440
0!
0+
#445
1!
1+
b1001 .
10
12
1'
1?
1C
b1010 A
06
15
#450
0!
0+
#455
1!
1+
b1010 .
00
02
0'
1&
0?
0C
b0 A
b100 I
09
08
17
05
03
#460
0!
0+
#465
1!
1+
b0 .
b100 /
0*
0)
1(
0&
0$
b1 A
16
#470
0!
0+
#475
1!
1+
b1 .
1'
b10 A
06
15
#480
0!
0+
#485
1!
1+
b10 .
0'
1&
b11 A
16
#490
0!
0+
#495
1!
1+
b11 .
1'
b100 A
06
05
14
#500
0!
0+
#505
1!
1+
b100 .
0'
0&
1%
b101 A
16
#510
0!
0+
#515
1!
1+
b101 .
1'
b110 A
06
15
#520
0!
0+
#525
1!
1+
b110 .
0'
1&
b111 A
16
#530
0!
0+
#535
1!
1+
b111 .
1'
b1000 A
06
05
04
13
#540
0!
0+
#545
1!
1+
b1000 .
0'
0&
0%
1$
b1001 A
16
#550
0!
0+
#555
1!
1+
b1001 .
10
12
1'
1?
1C
b1010 A
06
15
#560
0!
0+
#565
1!
1+
b1010 .
00
02
0'
1&
0?
0C
b0 A
b101 I
19
05
03
#570
0!
0+
#575
1!
1+
b0 .
b101 /
1*
0&
0$
b1 A
16
#580
0!
0+
#585
1!
1+
b1 .
1'
b10 A
06
15
#590
0!
0+
#595
1!
1+
b10 .
0'
1&
b11 A
16
#600
0!
0+
#605
1!
1+
b11 .
1'
b100 A
06
05
14
#610
0!
0+
#615
1!
1+
b100 .
0'
0&
1%
b101 A
16
#620
0!
0+
#625
1!
1+
b101 .
1'
b110 A
06
15
#630
0!
0+
#635
1!
1+
b110 .
0'
1&
b111 A
16
#640
0!
0+
#645
1!
1+
b111 .
1'
b1000 A
06
05
04
13
#650
0!
0+
#655
1!
1+
b1000 .
0'
0&
0%
1$
b1001 A
16
#660
0!
0+
#665
1!
1+
b1001 .
10
11
1'
1?
1G
b1010 A
06
15
#670
0!
0+
#675
1!
1+
b1010 .
00
01
0'
1&
0?
0G
b0 A
b0 I
09
07
05
03
#680
0!
0+
#685
1!
1+
b0 .
b0 /
0*
0(
0&
0$
b1 A
16
#690
0!
0+
#695
1!
1+
b1 .
1'
b10 A
06
15
#700
0!
0+
#705
1!
1+
b10 .
0'
1&
b11 A
16
#710
0!
0+
#715
1!
1+
b11 .
1'
b100 A
06
05
14
#720
0!
0+
#725
1!
1+
b100 .
0'
0&
1%
b101 A
16
#730
0!
0+
#735
1!
1+
b101 .
1'
b110 A
06
15
#740
0!
0+
#745
1!
1+
b110 .
0'
1&
b111 A
16
#750
0!
0+
#755
1!
1+
b111 .
1'
b1000 A
06
05
04
13
#760
0!
0+
#765
1!
1+
b1000 .
0'
0&
0%
1$
b1001 A
16
#770
0!
0+
#775
1!
1+
b1001 .
10
12
1'
1?
1C
b1010 A
06
15
#780
0!
0+
#785
1!
1+
b1010 .
00
02
0'
1&
0?
0C
b0 A
b1 I
19
05
03
#790
0!
0+
#795
1!
1+
b0 .
b1 /
1*
0&
0$
b1 A
16
#800
0!
0+
#805
1!
1+
b1 .
1'
b10 A
06
15
#810
0!
0+
#815
1!
1+
b10 .
0'
1&
b11 A
16
#820
0!
0+
#825
1!
1+
b11 .
1'
b100 A
06
05
14
#830
0!
0+
#835
1!
1+
b100 .
0'
0&
1%
b101 A
16
#840
0!
0+
#845
1!
1+
b101 .
1'
b110 A
06
15
#850
0!
0+
#855
1!
1+
b110 .
0'
1&
b111 A
16
#860
0!
0+
#865
1!
1+
b111 .
1'
b1000 A
06
05
04
13
#870
0!
0+
#875
1!
1+
b1000 .
0'
0&
0%
1$
b1001 A
16
#880
0!
0+
#885
1!
1+
b1001 .
10
12
1'
1?
1C
b1010 A
06
15
#890
0!
0+
#895
1!
1+
b1010 .
00
02
0'
1&
0?
0C
b0 A
b10 I
09
18
05
03
