2.4/data_plexer_en.v
module data_plexer_en #(parameter INPUT_WIDTH=4, 
                        parameter SEL=1) (

    input wire [(INPUT_WIDTH * (2**SEL) )-1:0] data_in,
    input wire [SEL-1:0] sel_ctrl,
    output reg [INPUT_WIDTH-1:0] data_out,
    output reg [(2**SEL)-1:0] data_en
    );

    wire [(2**SEL)-1:0] demux_mask = 1;

    always @ (sel_ctrl or data_in) begin
        data_out = data_in[sel_ctrl*INPUT_WIDTH +: INPUT_WIDTH];
        data_en = demux_mask << sel_ctrl;
    end

endmodule

2.4/counter_nbit.v
module counter_nbit #(parameter WIDTH = 4)(
    input clk,
    input reset,
    input enable,
    input [WIDTH-1:0] data,
    input load,
    input up_down,
    output reg [WIDTH-1:0] count
);

always @(posedge clk or posedge reset) begin
    if (reset)
        count <= 0;
    else if (load)
        count <= data;
    else if (enable)
        count <= up_down ? (count + 1'b1) : (count - 1'b1);
end

endmodule

2.4/timer_60.v
module timer_60(
    input clk,
    input reset,
    input enable,      // This enable should already be divided clock (e.g., every 5 cycles)
    output reg [3:0] low_digit,
    output reg [2:0] high_digit
);

    reg low_load;
    reg high_load;
    reg high_enable;

    wire [3:0] low_count;
    wire [2:0] high_count;

    // Internal counters for low and high digits
    counter_nbit #(.WIDTH(4)) LD (
        .clk(clk),
        .reset(reset),
        .enable(enable),
        .data(4'b0000),
        .load(low_load),
        .up_down(1'b1),
        .count(low_count)
    );

    counter_nbit #(.WIDTH(3)) HD (
        .clk(clk),
        .reset(reset),
        .enable(high_enable),
        .data(3'b000),
        .load(high_load),
        .up_down(1'b1),
        .count(high_count)
    );

    // Combinational logic to control loading and enabling counters
    always @(*) begin
        low_load = 0;
        high_load = 0;
        high_enable = 0;

        if (enable) begin
            if (low_count == 9 && high_count == 5) begin
                // At 59 → reset both counters
                low_load = 1;
                high_load = 1;
            end else if (low_count == 9) begin
                // At 9 → reset low digit and enable high digit to increment
                low_load = 1;
                high_enable = 1;
            end
        end
    end

    // Update outputs synchronously
    always @(posedge clk or posedge reset) begin
        if (reset) begin
            low_digit <= 0;
            high_digit <= 0;
        end else begin
            low_digit <= low_count;
            high_digit <= high_count;
        end
    end

endmodule

2.4/clk_divider.v
module clock_divider #(parameter CLK_DIV_INT = 10)(
    input clk,
    input reset,
    input pause,
    output reg rco_enable
);

localparam WIDTH = $clog2(CLK_DIV_INT);

wire [WIDTH-1:0] count;

counter_nbit #(.WIDTH(WIDTH)) cntr (
    .clk(clk),
    .reset(reset),
    .enable(~pause),
    .data((2**WIDTH) - CLK_DIV_INT),
    .load(rco_enable),
    .up_down(1'b1),
    .count(count)
);

initial rco_enable = 0;

always @(count) begin
    if (count == (2**WIDTH) - 1)
        rco_enable = 1'b1;
    else
        rco_enable = 1'b0;
end

endmodule

2.4/top_60.v
module top_60 #(parameter CLK_DIV_INT=5) (
    input clk,
    input reset,
    input pause,
    output [3:0] low_digit,
    output [2:0] high_digit,
    output [3:0] muxed_digits,
    output en_high_digit,
    output en_low_digit
);

    wire enable;

    // Clock divider for divide-by-5 enable signal
    clock_divider #(.CLK_DIV_INT(CLK_DIV_INT)) clkdiv_inst (
        .clk(clk),
        .reset(reset),
        .pause(pause),
        .rco_enable(enable)
    );

    timer_60 timer_inst (
        .clk(clk),
        .reset(reset),
        .enable(enable),
        .low_digit(low_digit),
        .high_digit(high_digit)
    );

    // Digit selector toggles every clock cycle for multiplexing
    reg sel_ctrl = 0;
    always @(posedge clk or posedge reset) begin
        if (reset)
            sel_ctrl <= 0;
        else
            sel_ctrl <= ~sel_ctrl;
    end

    wire [7:0] data_in = {1'b0, high_digit, low_digit};
    wire [1:0] data_en;
    wire [3:0] muxed_digits_wire;

    data_plexer_en #(.INPUT_WIDTH(4), .SEL(1)) mux_inst (
        .data_in(data_in),
        .sel_ctrl(sel_ctrl),
        .data_out(muxed_digits_wire),
        .data_en(data_en)
    );

    assign muxed_digits = muxed_digits_wire;
    assign en_low_digit = (sel_ctrl == 0) ? data_en[0] : 0;
    assign en_high_digit = (sel_ctrl == 1) ? data_en[1] : 0;

endmodule

2.4/top_60_tb.v
`timescale 1ns/1ns

module top_60_tb;

    reg clk = 0;
    reg reset = 1;
    reg pause = 0;
    wire [3:0] low_digit;
    wire [2:0] high_digit;
    wire [3:0] muxed_digits;
    wire en_high_digit;
    wire en_low_digit;

    // Instantiate top module
    top_60 #(.CLK_DIV_INT(5)) uut (
        .clk(clk),
        .reset(reset),
        .pause(pause),
        .low_digit(low_digit),
        .high_digit(high_digit),
        .muxed_digits(muxed_digits),
        .en_high_digit(en_high_digit),
        .en_low_digit(en_low_digit)
    );

    // Clock generation: 10ns period (100 MHz)
    always #5 clk = ~clk;

    initial begin
        $dumpfile("top_60_tb.vcd");
        $dumpvars(0, top_60_tb);

        // Release reset after a few clock cycles
        #20;
        reset = 0;

        // Let it run without pause for 800ns (~80 counts)
        #800;

        // Activate pause
        pause = 1;
        #100;

        // Resume
        pause = 0;
        #400;
    end

endmodule

2.4/top_60_tb.vcd
$date
	Sun Aug 03 00:22:49 2025
$end
$version
	ModelSim Version 2020.1
$end
$timescale
	1ns
$end

$scope module top_60_tb $end
$var reg 1 ! clk $end
$var reg 1 " reset $end
$var reg 1 # pause $end
$var wire 1 $ low_digit [3] $end
$var wire 1 % low_digit [2] $end
$var wire 1 & low_digit [1] $end
$var wire 1 ' low_digit [0] $end
$var wire 1 ( high_digit [2] $end
$var wire 1 ) high_digit [1] $end
$var wire 1 * high_digit [0] $end
$var wire 1 + muxed_digits [3] $end
$var wire 1 , muxed_digits [2] $end
$var wire 1 - muxed_digits [1] $end
$var wire 1 . muxed_digits [0] $end
$var wire 1 / en_high_digit $end
$var wire 1 0 en_low_digit $end

$scope module uut $end
$var parameter 32 1 CLK_DIV_INT $end
$var wire 1 2 clk $end
$var wire 1 3 reset $end
$var wire 1 4 pause $end
$var wire 1 $ low_digit [3] $end
$var wire 1 % low_digit [2] $end
$var wire 1 & low_digit [1] $end
$var wire 1 ' low_digit [0] $end
$var wire 1 ( high_digit [2] $end
$var wire 1 ) high_digit [1] $end
$var wire 1 * high_digit [0] $end
$var wire 1 + muxed_digits [3] $end
$var wire 1 , muxed_digits [2] $end
$var wire 1 - muxed_digits [1] $end
$var wire 1 . muxed_digits [0] $end
$var wire 1 / en_high_digit $end
$var wire 1 0 en_low_digit $end
$var wire 1 5 enable $end
$var reg 1 6 sel_ctrl $end
$var wire 1 7 data_in [7] $end
$var wire 1 8 data_in [6] $end
$var wire 1 9 data_in [5] $end
$var wire 1 : data_in [4] $end
$var wire 1 ; data_in [3] $end
$var wire 1 < data_in [2] $end
$var wire 1 = data_in [1] $end
$var wire 1 > data_in [0] $end
$var wire 1 ? data_en [1] $end
$var wire 1 @ data_en [0] $end
$var wire 1 A muxed_digits_wire [3] $end
$var wire 1 B muxed_digits_wire [2] $end
$var wire 1 C muxed_digits_wire [1] $end
$var wire 1 D muxed_digits_wire [0] $end

$scope module clkdiv_inst $end
$var parameter 32 E CLK_DIV_INT $end
$var parameter 32 F WIDTH $end
$var wire 1 2 clk $end
$var wire 1 3 reset $end
$var wire 1 4 pause $end
$var reg 1 G rco_enable $end
$var wire 1 H count [2] $end
$var wire 1 I count [1] $end
$var wire 1 J count [0] $end

$scope module cntr $end
$var parameter 32 K WIDTH $end
$var wire 1 2 clk $end
$var wire 1 3 reset $end
$var wire 1 L enable $end
$var wire 1 M data [2] $end
$var wire 1 N data [1] $end
$var wire 1 O data [0] $end
$var wire 1 P load $end
$var wire 1 Q up_down $end
$var reg 3 R count [2:0] $end
$upscope $end
$upscope $end

$scope module timer_inst $end
$var wire 1 2 clk $end
$var wire 1 3 reset $end
$var wire 1 5 enable $end
$var reg 4 S low_digit [3:0] $end
$var reg 3 T high_digit [2:0] $end
$var reg 1 U low_load $end
$var reg 1 V high_load $end
$var reg 1 W high_enable $end
$var wire 1 X low_count [3] $end
$var wire 1 Y low_count [2] $end
$var wire 1 Z low_count [1] $end
$var wire 1 [ low_count [0] $end
$var wire 1 \ high_count [2] $end
$var wire 1 ] high_count [1] $end
$var wire 1 ^ high_count [0] $end

$scope module LD $end
$var parameter 32 _ WIDTH $end
$var wire 1 2 clk $end
$var wire 1 3 reset $end
$var wire 1 5 enable $end
$var wire 1 ` data [3] $end
$var wire 1 a data [2] $end
$var wire 1 b data [1] $end
$var wire 1 c data [0] $end
$var wire 1 d load $end
$var wire 1 e up_down $end
$var reg 4 f count [3:0] $end
$upscope $end

$scope module HD $end
$var parameter 32 g WIDTH $end
$var wire 1 2 clk $end
$var wire 1 3 reset $end
$var wire 1 h enable $end
$var wire 1 i data [2] $end
$var wire 1 j data [1] $end
$var wire 1 k data [0] $end
$var wire 1 l load $end
$var wire 1 m up_down $end
$var reg 3 n count [2:0] $end
$upscope $end
$upscope $end

$scope module mux_inst $end
$var parameter 32 o INPUT_WIDTH $end
$var parameter 32 p SEL $end
$var wire 1 7 data_in [7] $end
$var wire 1 8 data_in [6] $end
$var wire 1 9 data_in [5] $end
$var wire 1 : data_in [4] $end
$var wire 1 ; data_in [3] $end
$var wire 1 < data_in [2] $end
$var wire 1 = data_in [1] $end
$var wire 1 > data_in [0] $end
$var wire 1 q sel_ctrl [0] $end
$var reg 4 r data_out [3:0] $end
$var reg 2 s data_en [1:0] $end
$var wire 1 t demux_mask [1] $end
$var wire 1 u demux_mask [0] $end
$upscope $end
$upscope $end
$upscope $end
$enddefinitions $end
#0
$dumpvars
0!
1"
0#
0G
b0 R
b0 S
b0 T
0U
0V
0W
b0 f
b0 n
06
b0 r
b1 s
b101 1
b101 E
b11 F
b11 K
b100 _
b11 g
b100 o
b1 p
0'
0&
0%
0$
0*
0)
0(
0.
0-
0,
0+
0/
10
05
0J
0I
0H
0[
0Z
0Y
0X
0^
0]
0\
0>
0=
0<
0;
0:
09
08
07
1@
0?
0D
0C
0B
0A
1u
0t
04
13
02
0q
1Q
0P
1L
1O
1N
0M
1m
0l
0k
0j
0i
0h
1e
0d
0c
0b
0a
0`
$end
#5
1!
12
#10
0!
02
#15
1!
12
#20
0"
0!
03
02
#25
1!
12
b1 R
16
00
1J
1q
b10 s
0@
1?
1/
#30
0!
02
#35
1!
12
b10 R
06
0/
0J
1I
0q
b1 s
1@
0?
10
#40
0!
02
#45
1!
12
b11 R
16
00
1J
1q
b10 s
0@
1?
1/
#50
0!
02
#55
1!
12
b100 R
06
0/
0J
0I
1H
0q
b1 s
1@
0?
10
#60
0!
02
#65
1!
12
b101 R
16
00
1J
1q
b10 s
0@
1?
1/
#70
0!
02
#75
1!
12
b110 R
06
0/
0J
1I
0q
b1 s
1@
0?
10
#80
0!
02
#85
1!
12
b111 R
16
00
1J
1q
b10 s
1G
0@
1?
1P
1/
15
#90
0!
02
#95
1!
12
b11 R
b1 f
06
0/
1[
0H
0q
b1 s
0G
1@
0?
0P
10
05
#100
0!
02
#105
1!
12
b100 R
b1 S
16
00
1'
1q
1>
0J
0I
1H
b10 s
0@
1?
1/
#110
0!
02
#115
1!
12
b101 R
06
0/
1J
0q
b1 r
b1 s
1@
0?
1D
10
1.
#120
0!
02
#125
1!
12
b110 R
16
00
0J
1I
1q
b0 r
b10 s
0@
1?
0D
1/
0.
#130
0!
02
#135
1!
12
b111 R
06
0/
1J
0q
b1 r
b1 s
1G
1@
0?
1D
1P
10
1.
15
#140
0!
02
#145
1!
12
b11 R
b10 f
16
00
0[
1Z
0H
1q
b0 r
b10 s
0G
0@
1?
0D
0P
1/
0.
05
#150
0!
02
#155
1!
12
b100 R
b10 S
06
0/
0'
1&
0q
0>
1=
0J
0I
1H
b10 r
b1 s
1@
0?
1C
10
1-
#160
0!
02
#165
1!
12
b101 R
16
00
1J
1q
b0 r
b10 s
0@
1?
0C
1/
0-
#170
0!
02
#175
1!
12
b110 R
06
0/
0J
1I
0q
b10 r
b1 s
1@
0?
1C
10
1-
#180
0!
02
#185
1!
12
b111 R
16
00
1J
1q
b0 r
b10 s
1G
0@
1?
0C
1P
1/
0-
15
#190
0!
02
#195
1!
12
b11 R
b11 f
06
0/
1[
0H
0q
b10 r
b1 s
0G
1@
0?
1C
0P
10
1-
05
#200
0!
02
#205
1!
12
b100 R
b11 S
16
00
1'
1q
1>
0J
0I
1H
b0 r
b10 s
0@
1?
0C
1/
0-
#210
0!
02
#215
1!
12
b101 R
06
0/
1J
0q
b11 r
b1 s
1@
0?
1D
1C
10
1.
1-
#220
0!
02
#225
1!
12
b110 R
16
00
0J
1I
1q
b0 r
b10 s
0@
1?
0D
0C
1/
0.
0-
#230
0!
02
#235
1!
12
b111 R
06
0/
1J
0q
b11 r
b1 s
1G
1@
0?
1D
1C
1P
10
1.
1-
15
#240
0!
02
#245
1!
12
b11 R
b100 f
16
00
0[
0Z
1Y
0H
1q
b0 r
b10 s
0G
0@
1?
0D
0C
0P
1/
0.
0-
05
#250
0!
02
#255
1!
12
b100 R
b100 S
06
0/
0'
0&
1%
0q
0>
0=
1<
0J
0I
1H
b100 r
b1 s
1@
0?
1B
10
1,
#260
0!
02
#265
1!
12
b101 R
16
00
1J
1q
b0 r
b10 s
0@
1?
0B
1/
0,
#270
0!
02
#275
1!
12
b110 R
06
0/
0J
1I
0q
b100 r
b1 s
1@
0?
1B
10
1,
#280
0!
02
#285
1!
12
b111 R
16
00
1J
1q
b0 r
b10 s
1G
0@
1?
0B
1P
1/
0,
15
#290
0!
02
#295
1!
12
b11 R
b101 f
06
0/
1[
0H
0q
b100 r
b1 s
0G
1@
0?
1B
0P
10
1,
05
#300
0!
02
#305
1!
12
b100 R
b101 S
16
00
1'
1q
1>
0J
0I
1H
b0 r
b10 s
0@
1?
0B
1/
0,
#310
0!
02
#315
1!
12
b101 R
06
0/
1J
0q
b101 r
b1 s
1@
0?
1D
1B
10
1.
1,
#320
0!
02
#325
1!
12
b110 R
16
00
0J
1I
1q
b0 r
b10 s
0@
1?
0D
0B
1/
0.
0,
#330
0!
02
#335
1!
12
b111 R
06
0/
1J
0q
b101 r
b1 s
1G
1@
0?
1D
1B
1P
10
1.
1,
15
#340
0!
02
#345
1!
12
b11 R
b110 f
16
00
0[
1Z
0H
1q
b0 r
b10 s
0G
0@
1?
0D
0B
0P
1/
0.
0,
05
#350
0!
02
#355
1!
12
b100 R
b110 S
06
0/
0'
1&
0q
0>
1=
0J
0I
1H
b110 r
b1 s
1@
0?
1C
1B
10
1-
1,
#360
0!
02
#365
1!
12
b101 R
16
00
1J
1q
b0 r
b10 s
0@
1?
0C
0B
1/
0-
0,
#370
0!
02
#375
1!
12
b110 R
06
0/
0J
1I
0q
b110 r
b1 s
1@
0?
1C
1B
10
1-
1,
#380
0!
02
#385
1!
12
b111 R
16
00
1J
1q
b0 r
b10 s
1G
0@
1?
0C
0B
1P
1/
0-
0,
15
#390
0!
02
#395
1!
12
b11 R
b111 f
06
0/
1[
0H
0q
b110 r
b1 s
0G
1@
0?
1C
1B
0P
10
1-
1,
05
#400
0!
02
#405
1!
12
b100 R
b111 S
16
00
1'
1q
1>
0J
0I
1H
b0 r
b10 s
0@
1?
0C
0B
1/
0-
0,
#410
0!
02
#415
1!
12
b101 R
06
0/
1J
0q
b111 r
b1 s
1@
0?
1D
1C
1B
10
1.
1-
1,
#420
0!
02
#425
1!
12
b110 R
16
00
0J
1I
1q
b0 r
b10 s
0@
1?
0D
0C
0B
1/
0.
0-
0,
#430
0!
02
#435
1!
12
b111 R
06
0/
1J
0q
b111 r
b1 s
1G
1@
0?
1D
1C
1B
1P
10
1.
1-
1,
15
#440
0!
02
#445
1!
12
b11 R
b1000 f
16
00
0[
0Z
0Y
1X
0H
1q
b0 r
b10 s
0G
0@
1?
0D
0C
0B
0P
1/
0.
0-
0,
05
#450
0!
02
#455
1!
12
b100 R
b1000 S
06
0/
0'
0&
0%
1$
0q
0>
0=
0<
1;
0J
0I
1H
b1000 r
b1 s
1@
0?
1A
10
1+
#460
0!
02
#465
1!
12
b101 R
16
00
1J
1q
b0 r
b10 s
0@
1?
0A
1/
0+
#470
0!
02
#475
1!
12
b110 R
06
0/
0J
1I
0q
b1000 r
b1 s
1@
0?
1A
10
1+
#480
0!
02
#485
1!
12
b111 R
16
00
1J
1q
b0 r
b10 s
1G
0@
1?
0A
1P
1/
0+
15
#490
0!
02
#495
1!
12
b11 R
b1001 f
06
0/
1[
0H
0q
b1000 r
b1 s
0G
1U
1W
1@
0?
1A
0P
1d
1h
10
1+
05
0U
0W
0d
0h
#500
0!
02
#505
1!
12
b100 R
b1001 S
16
00
1'
1q
1>
0J
0I
1H
b0 r
b10 s
0@
1?
0A
1/
0+
#510
0!
02
#515
1!
12
b101 R
06
0/
1J
0q
b1001 r
b1 s
1@
0?
1D
1A
10
1.
1+
#520
0!
02
#525
1!
12
b110 R
16
00
0J
1I
1q
b0 r
b10 s
0@
1?
0D
0A
1/
0.
0+
#530
0!
02
#535
1!
12
b111 R
06
0/
1J
0q
b1001 r
b1 s
1G
1@
0?
1D
1A
1P
10
1.
1+
15
1U
1W
1d
1h
#540
0!
02
#545
1!
12
b11 R
b0 f
b1 n
16
00
1^
0[
0X
0H
1q
b0 r
b10 s
0G
0U
0W
0@
1?
0D
0A
0P
0d
0h
1/
0.
0+
05
#550
0!
02
#555
1!
12
b100 R
b0 S
b1 T
06
0/
1*
0'
0$
0q
0>
0;
1:
0J
0I
1H
b1 s
1@
0?
10
#560
0!
02
#565
1!
12
b101 R
16
00
1J
1q
b1 r
b10 s
0@
1?
1D
1/
1.
#570
0!
02
#575
1!
12
b110 R
06
0/
0J
1I
0q
b0 r
b1 s
1@
0?
0D
10
0.
#580
0!
02
#585
1!
12
b111 R
16
00
1J
1q
b1 r
b10 s
1G
0@
1?
1D
1P
1/
1.
15
#590
0!
02
#595
1!
12
b11 R
b1 f
06
0/
1[
0H
0q
b0 r
b1 s
0G
1@
0?
0D
0P
10
0.
05
#600
0!
02
#605
1!
12
b100 R
b1 S
16
00
1'
1q
1>
0J
0I
1H
b1 r
b10 s
0@
1?
1D
1/
1.
#610
0!
02
#615
1!
12
b101 R
06
0/
1J
0q
b1 s
1@
0?
10
#620
0!
02
#625
1!
12
b110 R
16
00
0J
1I
1q
b10 s
0@
1?
1/
#630
0!
02
#635
1!
12
b111 R
06
0/
1J
0q
b1 s
1G
1@
0?
1P
10
15
#640
0!
02
#645
1!
12
b11 R
b10 f
16
00
0[
1Z
0H
1q
b10 s
0G
0@
1?
0P
1/
05
#650
0!
02
#655
1!
12
b100 R
b10 S
06
0/
0'
1&
0q
0>
1=
0J
0I
1H
b10 r
b1 s
1@
0?
0D
1C
10
0.
1-
#660
0!
02
#665
1!
12
b101 R
16
00
1J
1q
b1 r
b10 s
0@
1?
1D
0C
1/
1.
0-
#670
0!
02
#675
1!
12
b110 R
06
0/
0J
1I
0q
b10 r
b1 s
1@
0?
0D
1C
10
0.
1-
#680
0!
02
#685
1!
12
b111 R
16
00
1J
1q
b1 r
b10 s
1G
0@
1?
1D
0C
1P
1/
1.
0-
15
#690
0!
02
#695
1!
12
b11 R
b11 f
06
0/
1[
0H
0q
b10 r
b1 s
0G
1@
0?
0D
1C
0P
10
0.
1-
05
#700
0!
02
#705
1!
12
b100 R
b11 S
16
00
1'
1q
1>
0J
0I
1H
b1 r
b10 s
0@
1?
1D
0C
1/
1.
0-
#710
0!
02
#715
1!
12
b101 R
06
0/
1J
0q
b11 r
b1 s
1@
0?
1C
10
1-
#720
0!
02
#725
1!
12
b110 R
16
00
0J
1I
1q
b1 r
b10 s
0@
1?
0C
1/
0-
#730
0!
02
#735
1!
12
b111 R
06
0/
1J
0q
b11 r
b1 s
1G
1@
0?
1C
1P
10
1-
15
#740
0!
02
#745
1!
12
b11 R
b100 f
16
00
0[
0Z
1Y
0H
1q
b1 r
b10 s
0G
0@
1?
0C
0P
1/
0-
05
#750
0!
02
#755
1!
12
b100 R
b100 S
06
0/
0'
0&
1%
0q
0>
0=
1<
0J
0I
1H
b100 r
b1 s
1@
0?
0D
1B
10
0.
1,
#760
0!
02
#765
1!
12
b101 R
16
00
1J
1q
b1 r
b10 s
0@
1?
1D
0B
1/
1.
0,
#770
0!
02
#775
1!
12
b110 R
06
0/
0J
1I
0q
b100 r
b1 s
1@
0?
0D
1B
10
0.
1,
#780
0!
02
#785
1!
12
b111 R
16
00
1J
1q
b1 r
b10 s
1G
0@
1?
1D
0B
1P
1/
1.
0,
15
#790
0!
02
#795
1!
12
b11 R
b101 f
06
0/
1[
0H
0q
b100 r
b1 s
0G
1@
0?
0D
1B
0P
10
0.
1,
05
#800
0!
02
#805
1!
12
b100 R
b101 S
16
00
1'
1q
1>
0J
0I
1H
b1 r
b10 s
0@
1?
1D
0B
1/
1.
0,
#810
0!
02
#815
1!
12
b101 R
06
0/
1J
0q
b101 r
b1 s
1@
0?
1B
10
1,
#820
1#
0!
14
0L
02
#825
1!
12
16
00
1q
b1 r
b10 s
0@
1?
0B
1/
0,
#830
0!
02
#835
1!
12
06
0/
0q
b101 r
b1 s
1@
0?
1B
10
1,
#840
0!
02
#845
1!
12
16
00
1q
b1 r
b10 s
0@
1?
0B
1/
0,
#850
0!
02
#855
1!
12
06
0/
0q
b101 r
b1 s
1@
0?
1B
10
1,
#860
0!
02
#865
1!
12
16
00
1q
b1 r
b10 s
0@
1?
0B
1/
0,
#870
0!
02
#875
1!
12
06
0/
0q
b101 r
b1 s
1@
0?
1B
10
1,
#880
0!
02
#885
1!
12
16
00
1q
b1 r
b10 s
0@
1?
0B
1/
0,
#890
0!
02
#895
1!
12
06
0/
0q
b101 r
b1 s
1@
0?
1B
10
1,
#900
0!
02
#905
1!
12
16
00
1q
b1 r
b10 s
0@
1?
0B
1/
0,
#910
0!
02
#915
1!
12
06
0/
0q
b101 r
b1 s
1@
0?
1B
10
1,
#920
0#
0!
04
1L
02
#925
1!
12
b110 R
16
00
0J
1I
1q
b1 r
b10 s
0@
1?
0B
1/
0,
#930
0!
02
#935
1!
12
b111 R
06
0/
1J
0q
b101 r
b1 s
1G
1@
0?
1B
1P
10
1,
15
#940
0!
02
#945
1!
12
b11 R
b110 f
16
00
0[
1Z
0H
1q
b1 r
b10 s
0G
0@
1?
0B
0P
1/
0,
05
#950
0!
02
#955
1!
12
b100 R
b110 S
06
0/
0'
1&
0q
0>
1=
0J
0I
1H
b110 r
b1 s
1@
0?
0D
1C
1B
10
0.
1-
1,
#960
0!
02
#965
1!
12
b101 R
16
00
1J
1q
b1 r
b10 s
0@
1?
1D
0C
0B
1/
1.
0-
0,
#970
0!
02
#975
1!
12
b110 R
06
0/
0J
1I
0q
b110 r
b1 s
1@
0?
0D
1C
1B
10
0.
1-
1,
#980
0!
02
#985
1!
12
b111 R
16
00
1J
1q
b1 r
b10 s
1G
0@
1?
1D
0C
0B
1P
1/
1.
0-
0,
15
#990
0!
02
#995
1!
12
b11 R
b111 f
06
0/
1[
0H
0q
b110 r
b1 s
0G
1@
0?
0D
1C
1B
0P
10
0.
1-
1,
05
#1000
0!
02
#1005
1!
12
b100 R
b111 S
16
00
1'
1q
1>
0J
0I
1H
b1 r
b10 s
0@
1?
1D
0C
0B
1/
1.
0-
0,
#1010
0!
02
#1015
1!
12
b101 R
06
0/
1J
0q
b111 r
b1 s
1@
0?
1C
1B
10
1-
1,
#1020
0!
02
#1025
1!
12
b110 R
16
00
0J
1I
1q
b1 r
b10 s
0@
1?
0C
0B
1/
0-
0,
#1030
0!
02
#1035
1!
12
b111 R
06
0/
1J
0q
b111 r
b1 s
1G
1@
0?
1C
1B
1P
10
1-
1,
15
#1040
0!
02
#1045
1!
12
b11 R
b1000 f
16
00
0[
0Z
0Y
1X
0H
1q
b1 r
b10 s
0G
0@
1?
0C
0B
0P
1/
0-
0,
05
#1050
0!
02
#1055
1!
12
b100 R
b1000 S
06
0/
0'
0&
0%
1$
0q
0>
0=
0<
1;
0J
0I
1H
b1000 r
b1 s
1@
0?
0D
1A
10
0.
1+
#1060
0!
02
#1065
1!
12
b101 R
16
00
1J
1q
b1 r
b10 s
0@
1?
1D
0A
1/
1.
0+
#1070
0!
02
#1075
1!
12
b110 R
06
0/
0J
1I
0q
b1000 r
b1 s
1@
0?
0D
1A
10
0.
1+
#1080
0!
02
#1085
1!
12
b111 R
16
00
1J
1q
b1 r
b10 s
1G
0@
1?
1D
0A
1P
1/
1.
0+
15
#1090
0!
02
#1095
1!
12
b11 R
b1001 f
06
0/
1[
0H
0q
b1000 r
b1 s
0G
1U
1W
1@
0?
0D
1A
0P
1d
1h
10
0.
1+
05
0U
0W
0d
0h
#1100
0!
02
#1105
1!
12
b100 R
b1001 S
16
00
1'
1q
1>
0J
0I
1H
b1 r
b10 s
0@
1?
1D
0A
1/
1.
0+
#1110
0!
02
#1115
1!
12
b101 R
06
0/
1J
0q
b1001 r
b1 s
1@
0?
1A
10
1+
#1120
0!
02
#1125
1!
12
b110 R
16
00
0J
1I
1q
b1 r
b10 s
0@
1?
0A
1/
0+
#1130
0!
02
#1135
1!
12
b111 R
06
0/
1J
0q
b1001 r
b1 s
1G
1@
0?
1A
1P
10
1+
15
1U
1W
1d
1h
#1140
0!
02
#1145
1!
12
b11 R
b0 f
b10 n
16
00
0^
1]
0[
0X
0H
1q
b1 r
b10 s
0G
0U
0W
0@
1?
0A
0P
0d
0h
1/
0+
05
#1150
0!
02
#1155
1!
12
b100 R
b0 S
b10 T
06
0/
0*
1)
0'
0$
0q
0>
0;
0:
19
0J
0I
1H
b0 r
b1 s
1@
0?
0D
10
0.
#1160
0!
02
#1165
1!
12
b101 R
16
00
1J
1q
b10 r
b10 s
0@
1?
1C
1/
1-
#1170
0!
02
#1175
1!
12
b110 R
06
0/
0J
1I
0q
b0 r
b1 s
1@
0?
0C
10
0-
#1180
0!
02
#1185
1!
12
b111 R
16
00
1J
1q
b10 r
b10 s
1G
0@
1?
1C
1P
1/
1-
15
#1190
0!
02
#1195
1!
12
b11 R
b1 f
06
0/
1[
0H
0q
b0 r
b1 s
0G
1@
0?
0C
0P
10
0-
05
#1200
0!
02
#1205
1!
12
b100 R
b1 S
16
00
1'
1q
1>
0J
0I
1H
b10 r
b10 s
0@
1?
1C
1/
1-
#1210
0!
02
#1215
1!
12
b101 R
06
0/
1J
0q
b1 r
b1 s
1@
0?
1D
0C
10
1.
0-
#1220
0!
02
#1225
1!
12
b110 R
16
00
0J
1I
1q
b10 r
b10 s
0@
1?
0D
1C
1/
0.
1-
#1230
0!
02
#1235
1!
12
b111 R
06
0/
1J
0q
b1 r
b1 s
1G
1@
0?
1D
0C
1P
10
1.
0-
15
#1240
0!
02
#1245
1!
12
b11 R
b10 f
16
00
0[
1Z
0H
1q
b10 r
b10 s
0G
0@
1?
0D
1C
0P
1/
0.
1-
05
#1250
0!
02
#1255
1!
12
b100 R
b10 S
06
0/
0'
1&
0q
0>
1=
0J
0I
1H
b1 s
1@
0?
10
#1260
0!
02
#1265
1!
12
b101 R
16
00
1J
1q
b10 s
0@
1?
1/
#1270
0!
02
#1275
1!
12
b110 R
06
0/
0J
1I
0q
b1 s
1@
0?
10
#1280
0!
02
#1285
1!
12
b111 R
16
00
1J
1q
b10 s
1G
0@
1?
1P
1/
15
#1290
0!
02
#1295
1!
12
b11 R
b11 f
06
0/
1[
0H
0q
b1 s
0G
1@
0?
0P
10
05
#1300
0!
02
#1305
1!
12
b100 R
b11 S
16
00
1'
1q
1>
0J
0I
1H
b10 s
0@
1?
1/
#1310
0!
02
#1315
1!
12
b101 R
06
0/
1J
0q
b11 r
b1 s
1@
0?
1D
10
1.
#1320
0!
02
#1325
1!
12
b110 R
16
00
0J
1I
1q
b10 r
b10 s
0@
1?
0D
1/
0.
#1330
0!
02
#1335
1!
12
b111 R
06
0/
1J
0q
b11 r
b1 s
1G
1@
0?
1D
1P
10
1.
15
#1340
0!
02
#1345
1!
12
b11 R
b100 f
16
00
0[
0Z
1Y
0H
1q
b10 r
b10 s
0G
0@
1?
0D
0P
1/
0.
05
#1350
0!
02
#1355
1!
12
b100 R
b100 S
06
0/
0'
0&
1%
0q
0>
0=
1<
0J
0I
1H
b100 r
b1 s
1@
0?
0C
1B
10
0-
1,
#1360
0!
02
#1365
1!
12
b101 R
16
00
1J
1q
b10 r
b10 s
0@
1?
1C
0B
1/
1-
0,
#1370
0!
02
#1375
1!
12
b110 R
06
0/
0J
1I
0q
b100 r
b1 s
1@
0?
0C
1B
10
0-
1,
#1380
0!
02
#1385
1!
12
b111 R
16
00
1J
1q
b10 r
b10 s
1G
0@
1?
1C
0B
1P
1/
1-
0,
15
#1390
0!
02
#1395
1!
12
b11 R
b101 f
06
0/
1[
0H
0q
b100 r
b1 s
0G
1@
0?
0C
1B
0P
10
0-
1,
05
#1400
0!
02
#1405
1!
12
b100 R
b101 S
16
00
1'
1q
1>
0J
0I
1H
b10 r
b10 s
0@
1?
1C
0B
1/
1-
0,
#1410
0!
02
#1415
1!
12
b101 R
06
0/
1J
0q
b101 r
b1 s
1@
0?
1D
0C
1B
10
1.
0-
1,
#1420
0!
02
#1425
1!
12
b110 R
16
00
0J
1I
1q
b10 r
b10 s
0@
1?
0D
1C
0B
1/
0.
1-
0,
#1430
0!
02
#1435
1!
12
b111 R
06
0/
1J
0q
b101 r
b1 s
1G
1@
0?
1D
0C
1B
1P
10
1.
0-
1,
15
#1440
0!
02
#1445
1!
12
b11 R
b110 f
16
00
0[
1Z
0H
1q
b10 r
b10 s
0G
0@
1?
0D
1C
0B
0P
1/
0.
1-
0,
05
#1450
0!
02
#1455
1!
12
b100 R
b110 S
06
0/
0'
1&
0q
0>
1=
0J
0I
1H
b110 r
b1 s
1@
0?
1B
10
1,
#1460
0!
02
#1465
1!
12
b101 R
16
00
1J
1q
b10 r
b10 s
0@
1?
0B
1/
0,
#1470
0!
02
